Metadata-Version: 2.1
Name: text-convert-unicode
Version: 0.0.2
Summary: text_convert_unicode
Home-page: https://github.com/DaniloTomassoni/Text_Convert_Unicode
Author: Danilo Tomassoni
Author-email: danilothomassoni@gmail.com
License: MIT
Platform: Windows
Platform: Linux
License-File: LICENSE.txt
